fhir_sheets/__init__.py
fhir_sheets/__init__.pyi
fhir_sheets/cli/__init__.py
fhir_sheets/cli/__init__.pyi
fhir_sheets/cli/main.py
fhir_sheets/cli/main.pyi
fhir_sheets/core/__init__.py
fhir_sheets/core/__init__.pyi
fhir_sheets/core/config/FhirSheetsConfiguration.py
fhir_sheets/core/conversion.py
fhir_sheets/core/conversion.pyi
fhir_sheets/core/fhir_formatting.py
fhir_sheets/core/fhir_formatting.pyi
fhir_sheets/core/model/__init__.py
fhir_sheets/core/model/__init__.pyi
fhir_sheets/core/model/cohort_data_entity.py
fhir_sheets/core/model/cohort_data_entity.pyi
fhir_sheets/core/model/common.py
fhir_sheets/core/model/common.pyi
fhir_sheets/core/model/resource_definition_entity.py
fhir_sheets/core/model/resource_definition_entity.pyi
fhir_sheets/core/model/resource_link_entity.py
fhir_sheets/core/model/resource_link_entity.pyi
fhir_sheets/core/read_input.py
fhir_sheets/core/read_input.pyi
fhir_sheets/core/special_values.py
fhir_sheets/core/special_values.pyi
fhir_sheets/core/util.py
fhir_sheets/core/util.pyi
fhir_sheets/util/CustomLoggingFormatter.py
fhir_sheets/util/__init__.py
fhir_sheets-2.2.2.dist-info/METADATA
fhir_sheets-2.2.2.dist-info/WHEEL
fhir_sheets-2.2.2.dist-info/licenses/LICENSE
fhir_sheets-2.2.2.dist-info/RECORD
